alibabacloud_imp_room20210515/__init__.py
alibabacloud_imp_room20210515/client.py
alibabacloud_imp_room20210515/models.py
alibabacloud_imp_room20210515_py2-2.1.0.dist-info/LICENSE
alibabacloud_imp_room20210515_py2-2.1.0.dist-info/METADATA
alibabacloud_imp_room20210515_py2-2.1.0.dist-info/WHEEL
alibabacloud_imp_room20210515_py2-2.1.0.dist-info/top_level.txt
alibabacloud_imp_room20210515_py2-2.1.0.dist-info/RECORD
